dmxnet/__init__.py
dmxnet/esp.py
dmxnet/socketext.py
dmxnet-0.1.dist-info/LICENSE
dmxnet-0.1.dist-info/METADATA
dmxnet-0.1.dist-info/WHEEL
dmxnet-0.1.dist-info/entry_points.txt
dmxnet-0.1.dist-info/top_level.txt
dmxnet-0.1.dist-info/RECORD
